Workbook

Sheet XXXX
A1: =#REF! -> #REF!
A2: SUMMARY BUDGET
A3: =#REF! -> #REF!
A4: =#REF! -> #REF!
A6: SECTION | B6: DESCRIPTION | C6: TOTAL
A7: INCOME | B7: UMCOR Sources | C7: =XXXXFinRep!D9 -> #REF!
A8: INCOME | B8: Other Grants | C8: =XXXXFinRep!D10 -> 0
A9: INCOME | B9: Annual Conference - UMC | C9: =XXXXFinRep!D11 -> 0
A10: INCOME | B10: Partner Annual Conference Contribution | C10: =XXXXFinRep!D12 -> 0
A11: INCOME | B11: Ministry of Health/Government | C11: =XXXXFinRep!D13 -> 0
A12: INCOME | B12: Local Churches and Individuals | C12: =XXXXFinRep!D14 -> 0
A13: INCOME | B13: Others-In-Kind Donation/Matching Funds | C13: =XXXXFinRep!D15 -> #REF!
B14: TOTAL INCOME | C14: =XXXXFinRep!D16 -> #REF!
A17: SECTION | B17: DESCRIPTION | C17: TOTAL
A19: SECTION A | B19: PROGRAM PERSONNEL | C19: =#REF! -> #REF!
A20: SECTION B | B20: DIRECT PROGRAM COSTS | C20: =#REF! -> #REF!
B21: =#REF! -> #REF! | C21: =#REF! -> #REF!
B22: =#REF! -> #REF! | C22: =#REF! -> #REF!
B23: =#REF! -> #REF! | C23: =#REF! -> #REF!
B24: =#REF! -> #REF! | C24: =#REF! -> #REF!
B25: =#REF! -> #REF! | C25: =#REF! -> #REF!
A27: SECTION C | B27: OTHER DIRECT PROGRAM COSTS | C27: =#REF! -> #REF!
B28: Visibility & Publication Costs | C28: =#REF! -> #REF!
B29: Monitoring & Evaluation Costs | C29: =#REF! -> #REF!
B30: TOTAL DIRECT PROGRAM COSTS | C30: =SUM(C27,C20,C19) -> #REF!
A32: SECTION D | B32: PROGRAM SUPPORT COSTS | C32: =#REF! -> #REF!
A33: SECTION D.1: | B33: SUPPORT PERSONNEL | C33: =#REF! -> #REF!
A34: SECTION D.2: | B34: EQUIPMENT | C34: =#REF! -> #REF!
A35: SECTION D.3: | B35: OFFICE RENTAL AND SUPPLIES | C35: =#REF! -> #REF!
A36: SECTION D.4: | B36: TRAVEL | C36: =#REF! -> #REF!
A37: SECTION D.5: | B37: COMMUNICATION | C37: =#REF! -> #REF!
A38: SECTION D.6: | B38: OTHER OPERATIONAL COSTS | C38: =#REF! -> #REF!
B39: TOTAL PROGRAM SUPPORT COSTS | C39: =SUM(C33:C38) -> #REF!
A41: SECTION E | B41: IN-KIND/MATCHING FUNDS | C41: =#REF! -> #REF!
A44: TOTAL PROJECT COST | C44: =SUM(C30,C39,C41) -> #REF!
A46: NET INCOME (TOTAL INCOME - TOTAL EXPENSE) | C46: =C14-C44 -> #REF!

Sheet XXXXX
A1: =#REF! -> #REF!
A2: SUMMARY REPORT
A3: =#REF! -> #REF!
A4: =#REF! -> #REF!
A6: SECTION | B6: CODE | C6: DESCRIPTION | D6: APPROVED INCOME | E6: TOTAL INCOME | F6: BALANCE
A7: INCOME | B7: UMCOR | C7: UMCOR Sources | D7: =SUMIF(XXXXFinRep!$B:$B,XXXXX!B7,XXXXFinRep!$D:$D) -> #REF! | E7: =SUMIF(XXXXFinRep!$B:$B,XXXXX!B7,XXXXFinRep!$H:$H) -> #REF! | F7: =SUMIF(XXXXFinRep!$B:$B,XXXXX!B7,XXXXFinRep!$I:$I) -> #REF!
A8: INCOME | B8: GRA | C8: Other Grants | D8: =SUMIF(XXXXFinRep!$B:$B,XXXXX!B8,XXXXFinRep!$D:$D) -> 0 | E8: =SUMIF(XXXXFinRep!$B:$B,XXXXX!B8,XXXXFinRep!$H:$H) -> 0 | F8: =SUMIF(XXXXFinRep!$B:$B,XXXXX!B8,XXXXFinRep!$I:$I) -> 0
A9: INCOME | B9: ANC | C9: Annual Conference - UMC | D9: =SUMIF(XXXXFinRep!$B:$B,XXXXX!B9,XXXXFinRep!$D:$D) -> 0 | E9: =SUMIF(XXXXFinRep!$B:$B,XXXXX!B9,XXXXFinRep!$H:$H) -> 0 | F9: =SUMIF(XXXXFinRep!$B:$B,XXXXX!B9,XXXXFinRep!$I:$I) -> 0
A10: INCOME | B10: PAC | C10: Partner Annual Conference Contribution | D10: =SUMIF(XXXXFinRep!$B:$B,XXXXX!B10,XXXXFinRep!$D:$D) -> 0 | E10: =SUMIF(XXXXFinRep!$B:$B,XXXXX!B10,XXXXFinRep!$H:$H) -> 0 | F10: =SUMIF(XXXXFinRep!$B:$B,XXXXX!B10,XXXXFinRep!$I:$I) -> 0
A11: INCOME | B11: MoH | C11: Ministry of Health/Government | D11: =SUMIF(XXXXFinRep!$B:$B,XXXXX!B11,XXXXFinRep!$D:$D) -> 0 | E11: =SUMIF(XXXXFinRep!$B:$B,XXXXX!B11,XXXXFinRep!$H:$H) -> 0 | F11: =SUMIF(XXXXFinRep!$B:$B,XXXXX!B11,XXXXFinRep!$I:$I) -> 0
A12: INCOME | B12: LC | C12: Local Churches and Individuals | D12: =SUMIF(XXXXFinRep!$B:$B,XXXXX!B12,XXXXFinRep!$D:$D) -> 0 | E12: =SUMIF(XXXXFinRep!$B:$B,XXXXX!B12,XXXXFinRep!$H:$H) -> 0 | F12: =SUMIF(XXXXFinRep!$B:$B,XXXXX!B12,XXXXFinRep!$I:$I) -> 0
A13: INCOME | B13: OTH | C13: Others-In-Kind Donation/Matching Funds | D13: =SUMIF(XXXXFinRep!$B:$B,XXXXX!B13,XXXXFinRep!$D:$D) -> #REF! | E13: =SUMIF(XXXXFinRep!$B:$B,XXXXX!B13,XXXXFinRep!$H:$H) -> 0 | F13: =SUMIF(XXXXFinRep!$B:$B,XXXXX!B13,XXXXFinRep!$I:$I) -> #REF!
C14: TOTAL INCOME | D14: =SUM(D7:D13) -> #REF! | E14: =SUM(E7:E13) -> #REF! | F14: =SUM(F7:F13) -> #REF!
A17: SECTION | C17: DESCRIPTION | D17: TOTAL | E17: TOTAL | F17: TOTAL
A19: SECTION A | B19: A.1 | C19: PROGRAM PERSONNEL | D19: =SUMIF(XXXXFinRep!$B:$B,XXXXX!B19,XXXXFinRep!$D:$D) -> #REF! | E19: =SUMIF(XXXXFinRep!$B:$B,XXXXX!B19,XXXXFinRep!$H:$H) -> #REF! | F19: =SUMIF(XXXXFinRep!$B:$B,XXXXX!B19,XXXXFinRep!$I:$I) -> #REF!
A20: SECTION B | C20: DIRECT PROGRAM COSTS
B21: B.1 | C21: =#REF! -> #REF! | D21: =SUMIF(XXXXFinRep!$B:$B,XXXXX!B21,XXXXFinRep!$D:$D) -> #REF! | E21: =SUMIF(XXXXFinRep!$B:$B,XXXXX!B21,XXXXFinRep!$H:$H) -> #REF! | F21: =SUMIF(XXXXFinRep!$B:$B,XXXXX!B21,XXXXFinRep!$I:$I) -> #REF!
B22: B.2 | C22: =#REF! -> #REF! | D22: =SUMIF(XXXXFinRep!$B:$B,XXXXX!B22,XXXXFinRep!$D:$D) -> #REF! | E22: =SUMIF(XXXXFinRep!$B:$B,XXXXX!B22,XXXXFinRep!$H:$H) -> #REF! | F22: =SUMIF(XXXXFinRep!$B:$B,XXXXX!B22,XXXXFinRep!$I:$I) -> #REF!
B23: B.3 | C23: =#REF! -> #REF! | D23: =SUMIF(XXXXFinRep!$B:$B,XXXXX!B23,XXXXFinRep!$D:$D) -> #REF! | E23: =SUMIF(XXXXFinRep!$B:$B,XXXXX!B23,XXXXFinRep!$H:$H) -> #REF! | F23: =SUMIF(XXXXFinRep!$B:$B,XXXXX!B23,XXXXFinRep!$I:$I) -> #REF!
B24: B.4 | C24: =#REF! -> #REF! | D24: =SUMIF(XXXXFinRep!$B:$B,XXXXX!B24,XXXXFinRep!$D:$D) -> #REF! | E24: =SUMIF(XXXXFinRep!$B:$B,XXXXX!B24,XXXXFinRep!$H:$H) -> #REF! | F24: =SUMIF(XXXXFinRep!$B:$B,XXXXX!B24,XXXXFinRep!$I:$I) -> #REF!
B25: B.5 | C25: =#REF! -> #REF! | D25: =SUMIF(XXXXFinRep!$B:$B,XXXXX!B25,XXXXFinRep!$D:$D) -> #REF! | E25: =SUMIF(XXXXFinRep!$B:$B,XXXXX!B25,XXXXFinRep!$H:$H) -> #REF! | F25: =SUMIF(XXXXFinRep!$B:$B,XXXXX!B25,XXXXFinRep!$I:$I) -> #REF!
A27: SECTION C | C27: OTHER DIRECT PROGRAM COSTS
B28: C.1 | C28: Visibility & Publication Costs | D28: =SUMIF(XXXXFinRep!$B:$B,XXXXX!B28,XXXXFinRep!$D:$D) -> #REF! | E28: =SUMIF(XXXXFinRep!$B:$B,XXXXX!B28,XXXXFinRep!$H:$H) -> #REF! | F28: =SUMIF(XXXXFinRep!$B:$B,XXXXX!B28,XXXXFinRep!$I:$I) -> #REF!
B29: C.2 | C29: Monitoring & Evaluation Costs | D29: =SUMIF(XXXXFinRep!$B:$B,XXXXX!B29,XXXXFinRep!$D:$D) -> #REF! | E29: =SUMIF(XXXXFinRep!$B:$B,XXXXX!B29,XXXXFinRep!$H:$H) -> #REF! | F29: =SUMIF(XXXXFinRep!$B:$B,XXXXX!B29,XXXXFinRep!$I:$I) -> #REF!
C30: TOTAL DIRECT PROGRAM COSTS | D30: =SUM(D19:D29) -> #REF! | E30: =SUM(E19:E29) -> #REF! | F30: =SUM(F19:F29) -> #REF!
A32: SECTION D | C32: PROGRAM SUPPORT COSTS
B33: D.1 | C33: SUPPORT PERSONNEL | D33: =SUMIF(XXXXFinRep!$B:$B,XXXXX!B33,XXXXFinRep!$D:$D) -> #REF! | E33: =SUMIF(XXXXFinRep!$B:$B,XXXXX!B33,XXXXFinRep!$H:$H) -> #REF! | F33: =SUMIF(XXXXFinRep!$B:$B,XXXXX!B33,XXXXFinRep!$I:$I) -> #REF!
B34: D.2 | C34: EQUIPMENT | D34: =SUMIF(XXXXFinRep!$B:$B,XXXXX!B34,XXXXFinRep!$D:$D) -> #REF! | E34: =SUMIF(XXXXFinRep!$B:$B,XXXXX!B34,XXXXFinRep!$H:$H) -> #REF! | F34: =SUMIF(XXXXFinRep!$B:$B,XXXXX!B34,XXXXFinRep!$I:$I) -> #REF!
B35: D.3 | C35: OFFICE RENTAL AND SUPPLIES | D35: =SUMIF(XXXXFinRep!$B:$B,XXXXX!B35,XXXXFinRep!$D:$D) -> #REF! | E35: =SUMIF(XXXXFinRep!$B:$B,XXXXX!B35,XXXXFinRep!$H:$H) -> #REF! | F35: =SUMIF(XXXXFinRep!$B:$B,XXXXX!B35,XXXXFinRep!$I:$I) -> #REF!
B36: D.4 | C36: TRAVEL | D36: =SUMIF(XXXXFinRep!$B:$B,XXXXX!B36,XXXXFinRep!$D:$D) -> #REF! | E36: =SUMIF(XXXXFinRep!$B:$B,XXXXX!B36,XXXXFinRep!$H:$H) -> #REF! | F36: =SUMIF(XXXXFinRep!$B:$B,XXXXX!B36,XXXXFinRep!$I:$I) -> #REF!
B37: D.5 | C37: COMMUNICATION | D37: =SUMIF(XXXXFinRep!$B:$B,XXXXX!B37,XXXXFinRep!$D:$D) -> #REF! | E37: =SUMIF(XXXXFinRep!$B:$B,XXXXX!B37,XXXXFinRep!$H:$H) -> #REF! | F37: =SUMIF(XXXXFinRep!$B:$B,XXXXX!B37,XXXXFinRep!$I:$I) -> #REF!
B38: D.6 | C38: OTHER OPERATIONAL COSTS | D38: =SUMIF(XXXXFinRep!$B:$B,XXXXX!B38,XXXXFinRep!$D:$D) -> #REF! | E38: =SUMIF(XXXXFinRep!$B:$B,XXXXX!B38,XXXXFinRep!$H:$H) -> #REF! | F38: =SUMIF(XXXXFinRep!$B:$B,XXXXX!B38,XXXXFinRep!$I:$I) -> #REF!
C39: TOTAL PROGRAM SUPPORT COSTS | D39: =SUM(D33:D38) -> #REF! | E39: =SUM(E33:E38) -> #REF! | F39: =SUM(F33:F38) -> #REF!
C41: TOTAL UMCOR GRANT BUDGET | D41: =D39+D30 -> #REF! | E41: =E39+E30 -> #REF! | F41: =F39+F30 -> #REF!
A43: SECTION E | B43: E.1 | C43: IN-KIND/MATCHING FUNDS | D43: =SUMIF(XXXXFinRep!$B:$B,XXXXX!B43,XXXXFinRep!$D:$D) -> #REF! | E43: =SUMIF(XXXXFinRep!$B:$B,XXXXX!B43,XXXXFinRep!$H:$H) -> 0 | F43: =SUMIF(XXXXFinRep!$B:$B,XXXXX!B43,XXXXFinRep!$I:$I) -> #REF!
A46: TOTAL PROGRAM COST | D46: =SUM(D41,D43) -> #REF! | E46: =SUM(E41,E43) -> #REF! | F46: =SUM(F41,F43) -> #REF!
A48: NET INCOME (TOTAL INCOME - TOTAL EXPENSE) | D48: =D14-D46 -> #REF! | E48: =E14-E46 -> #REF! | F48: =F14-F46 -> #REF!

Sheet XXXXFinRep
B2: =#REF! -> #REF!
B3: FINANCIAL REPORT
B4: =#REF! -> #REF!
B5: =#REF! -> #REF!
C7: =#REF! -> #REF! | D7: =#REF! -> #REF!
B8: CODE | C8: DESCRIPTION | D8: APPROVED INCOME | E8: FUNDS RECEIVED PERIOD 1 | F8: FUNDS RECEIVED PERIOD 2 | G8: FUNDS RECEIVED PERIOD 3 | H8: TOTAL USD | I8: BALANCE USD
B9: UMCOR | C9: UMCOR Sources | D9: =D276 -> #REF! | E9: =SUMIF(#REF!,XXXXFinRep!B9,#REF!) -> #REF! | F9: =SUMIF(#REF!,XXXXFinRep!B9,#REF!) -> #REF! | G9: =SUMIF(#REF!,XXXXFinRep!B9,#REF!) -> #REF! | H9: =SUM(E9:G9) -> #REF! | I9: =D9-H9 -> #REF!
B10: GRA | C10: Other Grants | H10: =SUM(E10:G10) -> 0 | I10: =D10-H10 -> 0
B11: ANC | C11: Annual Conference - UMC | H11: =SUM(E11:G11) -> 0 | I11: =D11-H11 -> 0
B12: PAC | C12: Partner Annual Conference Contribution | H12: =SUM(E12:G12) -> 0 | I12: =D12-H12 -> 0
B13: MoH | C13: Ministry of Health/Government | H13: =SUM(E13:G13) -> 0 | I13: =D13-H13 -> 0
B14: LC | C14: Local Churches and Individuals | H14: =SUM(E14:G14) -> 0 | I14: =D14-H14 -> 0
B15: OTH | C15: Others-In-Kind Donation/Matching Funds | D15: =D289 -> #REF! | H15: =SUM(E15:G15) -> 0 | I15: =D15-H15 -> #REF!
C16: TOTAL INCOME | D16: =SUM(D9:D15) -> #REF! | E16: =SUM(E9:E15) -> #REF! | F16: =SUM(F9:F15) -> #REF! | G16: =SUM(G9:G15) -> #REF! | H16: =SUM(H9:H15) -> #REF! | I16: =SUM(I9:I15) -> #REF!
B18: CODE | C18: BUDGET DESCRIPTION | D18: APPROVED BUDGET USD | E18: EXPENSES PERIOD 1 USD | F18: EXPENSES PERIOD 2 USD | G18: EXPENSES PERIOD 3 USD | H18: TOTAL EXPENSES USD | I18: BALANCE USD
B19: SECTION A: PROGRAM PERSONNEL
C20: Position
A21: 1 | B21: =VLOOKUP(A21,#REF!,2,FALSE) -> #REF! | C21: =VLOOKUP(B21,#REF!,2,FALSE) -> #REF! | D21: =SUMIF(#REF!,XXXXFinRep!B21,#REF!) -> #REF! | E21: =SUMIF(#REF!,XXXXFinRep!B21,#REF!)+SUMIF(#REF!,XXXXFinRep!B21,#REF!) -> #REF! | F21: =SUMIF(#REF!,XXXXFinRep!B21,#REF!)+SUMIF(#REF!,XXXXFinRep!B21,#REF!) -> #REF! | G21: =SUMIF(#REF!,XXXXFinRep!B21,#REF!)+SUMIF(#REF!,XXXXFinRep!B21,#REF!) -> #REF! | H21: =SUM(E21,F21,G21) -> #REF! | I21: =SUM(D21-H21) -> #REF!
A22: 2 | B22: =VLOOKUP(A22,#REF!,2,FALSE) -> #REF! | C22: =VLOOKUP(B22,#REF!,2,FALSE) -> #REF! | D22: =SUMIF(#REF!,XXXXFinRep!B22,#REF!) -> #REF! | E22: =SUMIF(#REF!,XXXXFinRep!B22,#REF!)+SUMIF(#REF!,XXXXFinRep!B22,#REF!) -> #REF! | F22: =SUMIF(#REF!,XXXXFinRep!B22,#REF!)+SUMIF(#REF!,XXXXFinRep!B22,#REF!) -> #REF! | G22: =SUMIF(#REF!,XXXXFinRep!B22,#REF!)+SUMIF(#REF!,XXXXFinRep!B22,#REF!) -> #REF! | H22: =SUM(E22,F22,G22) -> #REF! | I22: =SUM(D22-H22) -> #REF!
A23: 3 | B23: =VLOOKUP(A23,#REF!,2,FALSE) -> #REF! | C23: =VLOOKUP(B23,#REF!,2,FALSE) -> #REF! | D23: =SUMIF(#REF!,XXXXFinRep!B23,#REF!) -> #REF! | E23: =SUMIF(#REF!,XXXXFinRep!B23,#REF!)+SUMIF(#REF!,XXXXFinRep!B23,#REF!) -> #REF! | F23: =SUMIF(#REF!,XXXXFinRep!B23,#REF!)+SUMIF(#REF!,XXXXFinRep!B23,#REF!) -> #REF! | G23: =SUMIF(#REF!,XXXXFinRep!B23,#REF!)+SUMIF(#REF!,XXXXFinRep!B23,#REF!) -> #REF! | H23: =SUM(E23,F23,G23) -> #REF! | I23: =SUM(D23-H23) -> #REF!
A24: 4 | B24: =VLOOKUP(A24,#REF!,2,FALSE) -> #REF! | C24: =VLOOKUP(B24,#REF!,2,FALSE) -> #REF! | D24: =SUMIF(#REF!,XXXXFinRep!B24,#REF!) -> #REF! | E24: =SUMIF(#REF!,XXXXFinRep!B24,#REF!)+SUMIF(#REF!,XXXXFinRep!B24,#REF!) -> #REF! | F24: =SUMIF(#REF!,XXXXFinRep!B24,#REF!)+SUMIF(#REF!,XXXXFinRep!B24,#REF!) -> #REF! | G24: =SUMIF(#REF!,XXXXFinRep!B24,#REF!)+SUMIF(#REF!,XXXXFinRep!B24,#REF!) -> #REF! | H24: =SUM(E24,F24,G24) -> #REF! | I24: =SUM(D24-H24) -> #REF!
A25: 5 | B25: =VLOOKUP(A25,#REF!,2,FALSE) -> #REF! | C25: =VLOOKUP(B25,#REF!,2,FALSE) -> #REF! | D25: =SUMIF(#REF!,XXXXFinRep!B25,#REF!) -> #REF! | E25: =SUMIF(#REF!,XXXXFinRep!B25,#REF!)+SUMIF(#REF!,XXXXFinRep!B25,#REF!) -> #REF! | F25: =SUMIF(#REF!,XXXXFinRep!B25,#REF!)+SUMIF(#REF!,XXXXFinRep!B25,#REF!) -> #REF! | G25: =SUMIF(#REF!,XXXXFinRep!B25,#REF!)+SUMIF(#REF!,XXXXFinRep!B25,#REF!) -> #REF! | H25: =SUM(E25,F25,G25) -> #REF! | I25: =SUM(D25-H25) -> #REF!
A26: 6 | B26: =VLOOKUP(A26,#REF!,2,FALSE) -> #REF! | C26: =VLOOKUP(B26,#REF!,2,FALSE) -> #REF! | D26: =SUMIF(#REF!,XXXXFinRep!B26,#REF!) -> #REF! | E26: =SUMIF(#REF!,XXXXFinRep!B26,#REF!)+SUMIF(#REF!,XXXXFinRep!B26,#REF!) -> #REF! | F26: =SUMIF(#REF!,XXXXFinRep!B26,#REF!)+SUMIF(#REF!,XXXXFinRep!B26,#REF!) -> #REF! | G26: =SUMIF(#REF!,XXXXFinRep!B26,#REF!)+SUMIF(#REF!,XXXXFinRep!B26,#REF!) -> #REF! | H26: =SUM(E26,F26,G26) -> #REF! | I26: =SUM(D26-H26) -> #REF!
A27: 7 | B27: =VLOOKUP(A27,#REF!,2,FALSE) -> #REF! | C27: =VLOOKUP(B27,#REF!,2,FALSE) -> #REF! | D27: =SUMIF(#REF!,XXXXFinRep!B27,#REF!) -> #REF! | E27: =SUMIF(#REF!,XXXXFinRep!B27,#REF!)+SUMIF(#REF!,XXXXFinRep!B27,#REF!) -> #REF! | F27: =SUMIF(#REF!,XXXXFinRep!B27,#REF!)+SUMIF(#REF!,XXXXFinRep!B27,#REF!) -> #REF! | G27: =SUMIF(#REF!,XXXXFinRep!B27,#REF!)+SUMIF(#REF!,XXXXFinRep!B27,#REF!) -> #REF! | H27: =SUM(E27,F27,G27) -> #REF! | I27: =SUM(D27-H27) -> #REF!
A28: 8 | B28: =VLOOKUP(A28,#REF!,2,FALSE) -> #REF! | C28: =VLOOKUP(B28,#REF!,2,FALSE) -> #REF! | D28: =SUMIF(#REF!,XXXXFinRep!B28,#REF!) -> #REF! | E28: =SUMIF(#REF!,XXXXFinRep!B28,#REF!)+SUMIF(#REF!,XXXXFinRep!B28,#REF!) -> #REF! | F28: =SUMIF(#REF!,XXXXFinRep!B28,#REF!)+SUMIF(#REF!,XXXXFinRep!B28,#REF!) -> #REF! | G28: =SUMIF(#REF!,XXXXFinRep!B28,#REF!)+SUMIF(#REF!,XXXXFinRep!B28,#REF!) -> #REF! | H28: =SUM(E28,F28,G28) -> #REF! | I28: =SUM(D28-H28) -> #REF!
A29: 9 | B29: =VLOOKUP(A29,#REF!,2,FALSE) -> #REF! | C29: =VLOOKUP(B29,#REF!,2,FALSE) -> #REF! | D29: =SUMIF(#REF!,XXXXFinRep!B29,#REF!) -> #REF! | E29: =SUMIF(#REF!,XXXXFinRep!B29,#REF!)+SUMIF(#REF!,XXXXFinRep!B29,#REF!) -> #REF! | F29: =SUMIF(#REF!,XXXXFinRep!B29,#REF!)+SUMIF(#REF!,XXXXFinRep!B29,#REF!) -> #REF! | G29: =SUMIF(#REF!,XXXXFinRep!B29,#REF!)+SUMIF(#REF!,XXXXFinRep!B29,#REF!) -> #REF! | H29: =SUM(E29,F29,G29) -> #REF! | I29: =SUM(D29-H29) -> #REF!
A30: 10 | B30: =VLOOKUP(A30,#REF!,2,FALSE) -> #REF! | C30: =VLOOKUP(B30,#REF!,2,FALSE) -> #REF! | D30: =SUMIF(#REF!,XXXXFinRep!B30,#REF!) -> #REF! | E30: =SUMIF(#REF!,XXXXFinRep!B30,#REF!)+SUMIF(#REF!,XXXXFinRep!B30,#REF!) -> #REF! | F30: =SUMIF(#REF!,XXXXFinRep!B30,#REF!)+SUMIF(#REF!,XXXXFinRep!B30,#REF!) -> #REF! | G30: =SUMIF(#REF!,XXXXFinRep!B30,#REF!)+SUMIF(#REF!,XXXXFinRep!B30,#REF!) -> #REF! | H30: =SUM(E30,F30,G30) -> #REF! | I30: =SUM(D30-H30) -> #REF!
B31: A.1 | C31: TOTAL PROGRAM PERSONNEL | D31: =SUM(D21:D30) -> #REF! | E31: =SUM(E21:E30) -> #REF! | F31: =SUM(F21:F30) -> #REF! | G31: =SUM(G21:G30) -> #REF! | H31: =SUM(H21:H30) -> #REF! | I31: =SUM(I21:I30) -> #REF!
B33: SECTION B: DIRECT PROGRAM COSTS
B34: 1 | C34: =VLOOKUP(B34,#REF!,2,FALSE) -> #REF!
A35: 11 | B35: =VLOOKUP(A35,#REF!,2,FALSE) -> #REF! | C35: =VLOOKUP(B35,#REF!,2,FALSE) -> #REF! | D35: =SUMIF(#REF!,XXXXFinRep!B35,#REF!) -> #REF! | E35: =SUMIF(#REF!,XXXXFinRep!B35,#REF!)+SUMIF(#REF!,XXXXFinRep!B35,#REF!) -> #REF! | F35: =SUMIF(#REF!,XXXXFinRep!B35,#REF!)+SUMIF(#REF!,XXXXFinRep!B35,#REF!) -> #REF! | G35: =SUMIF(#REF!,XXXXFinRep!B35,#REF!)+SUMIF(#REF!,XXXXFinRep!B35,#REF!) -> #REF! | H35: =SUM(E35,F35,G35) -> #REF! | I35: =SUM(D35-H35) -> #REF!
A36: 12 | B36: =VLOOKUP(A36,#REF!,2,FALSE) -> #REF! | C36: =VLOOKUP(B36,#REF!,2,FALSE) -> #REF! | D36: =SUMIF(#REF!,XXXXFinRep!B36,#REF!) -> #REF! | E36: =SUMIF(#REF!,XXXXFinRep!B36,#REF!)+SUMIF(#REF!,XXXXFinRep!B36,#REF!) -> #REF! | F36: =SUMIF(#REF!,XXXXFinRep!B36,#REF!)+SUMIF(#REF!,XXXXFinRep!B36,#REF!) -> #REF! | G36: =SUMIF(#REF!,XXXXFinRep!B36,#REF!)+SUMIF(#REF!,XXXXFinRep!B36,#REF!) -> #REF! | H36: =SUM(E36,F36,G36) -> #REF! | I36: =SUM(D36-H36) -> #REF!
A37: 13 | B37: =VLOOKUP(A37,#REF!,2,FALSE) -> #REF! | C37: =VLOOKUP(B37,#REF!,2,FALSE) -> #REF! | D37: =SUMIF(#REF!,XXXXFinRep!B37,#REF!) -> #REF! | E37: =SUMIF(#REF!,XXXXFinRep!B37,#REF!)+SUMIF(#REF!,XXXXFinRep!B37,#REF!) -> #REF! | F37: =SUMIF(#REF!,XXXXFinRep!B37,#REF!)+SUMIF(#REF!,XXXXFinRep!B37,#REF!) -> #REF! | G37: =SUMIF(#REF!,XXXXFinRep!B37,#REF!)+SUMIF(#REF!,XXXXFinRep!B37,#REF!) -> #REF! | H37: =SUM(E37,F37,G37) -> #REF! | I37: =SUM(D37-H37) -> #REF!
A38: 14 | B38: =VLOOKUP(A38,#REF!,2,FALSE) -> #REF! | C38: =VLOOKUP(B38,#REF!,2,FALSE) -> #REF! | D38: =SUMIF(#REF!,XXXXFinRep!B38,#REF!) -> #REF! | E38: =SUMIF(#REF!,XXXXFinRep!B38,#REF!)+SUMIF(#REF!,XXXXFinRep!B38,#REF!) -> #REF! | F38: =SUMIF(#REF!,XXXXFinRep!B38,#REF!)+SUMIF(#REF!,XXXXFinRep!B38,#REF!) -> #REF! | G38: =SUMIF(#REF!,XXXXFinRep!B38,#REF!)+SUMIF(#REF!,XXXXFinRep!B38,#REF!) -> #REF! | H38: =SUM(E38,F38,G38) -> #REF! | I38: =SUM(D38-H38) -> #REF!
A39: 15 | B39: =VLOOKUP(A39,#REF!,2,FALSE) -> #REF! | C39: =VLOOKUP(B39,#REF!,2,FALSE) -> #REF! | D39: =SUMIF(#REF!,XXXXFinRep!B39,#REF!) -> #REF! | E39: =SUMIF(#REF!,XXXXFinRep!B39,#REF!)+SUMIF(#REF!,XXXXFinRep!B39,#REF!) -> #REF! | F39: =SUMIF(#REF!,XXXXFinRep!B39,#REF!)+SUMIF(#REF!,XXXXFinRep!B39,#REF!) -> #REF! | G39: =SUMIF(#REF!,XXXXFinRep!B39,#REF!)+SUMIF(#REF!,XXXXFinRep!B39,#REF!) -> #REF! | H39: =SUM(E39,F39,G39) -> #REF! | I39: =SUM(D39-H39) -> #REF!
A40: 16 | B40: =VLOOKUP(A40,#REF!,2,FALSE) -> #REF! | C40: =VLOOKUP(B40,#REF!,2,FALSE) -> #REF! | D40: =SUMIF(#REF!,XXXXFinRep!B40,#REF!) -> #REF! | E40: =SUMIF(#REF!,XXXXFinRep!B40,#REF!)+SUMIF(#REF!,XXXXFinRep!B40,#REF!) -> #REF! | F40: =SUMIF(#REF!,XXXXFinRep!B40,#REF!)+SUMIF(#REF!,XXXXFinRep!B40,#REF!) -> #REF! | G40: =SUMIF(#REF!,XXXXFinRep!B40,#REF!)+SUMIF(#REF!,XXXXFinRep!B40,#REF!) -> #REF! | H40: =SUM(E40,F40,G40) -> #REF! | I40: =SUM(D40-H40) -> #REF!
A41: 17 | B41: =VLOOKUP(A41,#REF!,2,FALSE) -> #REF! | C41: =VLOOKUP(B41,#REF!,2,FALSE) -> #REF! | D41: =SUMIF(#REF!,XXXXFinRep!B41,#REF!) -> #REF! | E41: =SUMIF(#REF!,XXXXFinRep!B41,#REF!)+SUMIF(#REF!,XXXXFinRep!B41,#REF!) -> #REF! | F41: =SUMIF(#REF!,XXXXFinRep!B41,#REF!)+SUMIF(#REF!,XXXXFinRep!B41,#REF!) -> #REF! | G41: =SUMIF(#REF!,XXXXFinRep!B41,#REF!)+SUMIF(#REF!,XXXXFinRep!B41,#REF!) -> #REF! | H41: =SUM(E41,F41,G41) -> #REF! | I41: =SUM(D41-H41) -> #REF!
A42: 18 | B42: =VLOOKUP(A42,#REF!,2,FALSE) -> #REF! | C42: =VLOOKUP(B42,#REF!,2,FALSE) -> #REF! | D42: =SUMIF(#REF!,XXXXFinRep!B42,#REF!) -> #REF! | E42: =SUMIF(#REF!,XXXXFinRep!B42,#REF!)+SUMIF(#REF!,XXXXFinRep!B42,#REF!) -> #REF! | F42: =SUMIF(#REF!,XXXXFinRep!B42,#REF!)+SUMIF(#REF!,XXXXFinRep!B42,#REF!) -> #REF! | G42: =SUMIF(#REF!,XXXXFinRep!B42,#REF!)+SUMIF(#REF!,XXXXFinRep!B42,#REF!) -> #REF! | H42: =SUM(E42,F42,G42) -> #REF! | I42: =SUM(D42-H42) -> #REF!
A43: 19 | B43: =VLOOKUP(A43,#REF!,2,FALSE) -> #REF! | C43: =VLOOKUP(B43,#REF!,2,FALSE) -> #REF! | D43: =SUMIF(#REF!,XXXXFinRep!B43,#REF!) -> #REF! | E43: =SUMIF(#REF!,XXXXFinRep!B43,#REF!)+SUMIF(#REF!,XXXXFinRep!B43,#REF!) -> #REF! | F43: =SUMIF(#REF!,XXXXFinRep!B43,#REF!)+SUMIF(#REF!,XXXXFinRep!B43,#REF!) -> #REF! | G43: =SUMIF(#REF!,XXXXFinRep!B43,#REF!)+SUMIF(#REF!,XXXXFinRep!B43,#REF!) -> #REF! | H43: =SUM(E43,F43,G43) -> #REF! | I43: =SUM(D43-H43) -> #REF!
A44: 20 | B44: =VLOOKUP(A44,#REF!,2,FALSE) -> #REF! | C44: =VLOOKUP(B44,#REF!,2,FALSE) -> #REF! | D44: =SUMIF(#REF!,XXXXFinRep!B44,#REF!) -> #REF! | E44: =SUMIF(#REF!,XXXXFinRep!B44,#REF!)+SUMIF(#REF!,XXXXFinRep!B44,#REF!) -> #REF! | F44: =SUMIF(#REF!,XXXXFinRep!B44,#REF!)+SUMIF(#REF!,XXXXFinRep!B44,#REF!) -> #REF! | G44: =SUMIF(#REF!,XXXXFinRep!B44,#REF!)+SUMIF(#REF!,XXXXFinRep!B44,#REF!) -> #REF! | H44: =SUM(E44,F44,G44) -> #REF! | I44: =SUM(D44-H44) -> #REF!
A45: 21 | B45: =VLOOKUP(A45,#REF!,2,FALSE) -> #REF! | C45: =VLOOKUP(B45,#REF!,2,FALSE) -> #REF! | D45: =SUMIF(#REF!,XXXXFinRep!B45,#REF!) -> #REF! | E45: =SUMIF(#REF!,XXXXFinRep!B45,#REF!)+SUMIF(#REF!,XXXXFinRep!B45,#REF!) -> #REF! | F45: =SUMIF(#REF!,XXXXFinRep!B45,#REF!)+SUMIF(#REF!,XXXXFinRep!B45,#REF!) -> #REF! | G45: =SUMIF(#REF!,XXXXFinRep!B45,#REF!)+SUMIF(#REF!,XXXXFinRep!B45,#REF!) -> #REF! | H45: =SUM(E45,F45,G45) -> #REF! | I45: =SUM(D45-H45) -> #REF!
A46: 22 | B46: =VLOOKUP(A46,#REF!,2,FALSE) -> #REF! | C46: =VLOOKUP(B46,#REF!,2,FALSE) -> #REF! | D46: =SUMIF(#REF!,XXXXFinRep!B46,#REF!) -> #REF! | E46: =SUMIF(#REF!,XXXXFinRep!B46,#REF!)+SUMIF(#REF!,XXXXFinRep!B46,#REF!) -> #REF! | F46: =SUMIF(#REF!,XXXXFinRep!B46,#REF!)+SUMIF(#REF!,XXXXFinRep!B46,#REF!) -> #REF! | G46: =SUMIF(#REF!,XXXXFinRep!B46,#REF!)+SUMIF(#REF!,XXXXFinRep!B46,#REF!) -> #REF! | H46: =SUM(E46,F46,G46) -> #REF! | I46: =SUM(D46-H46) -> #REF!
... A54: 30 | B54: =VLOOKUP(A54,#REF!,2,FALSE) -> #REF! | C54: =VLOOKUP(B54,#REF!,2,FALSE) -> #REF! | D54: =SUMIF(#REF!,XXXXFinRep!B54,#REF!) -> #REF! | E54: =SUMIF(#REF!,XXXXFinRep!B54,#REF!)+SUMIF(#REF!,XXXXFinRep!B54,#REF!) -> #REF! | F54: =SUMIF(#REF!,XXXXFinRep!B54,#REF!)+SUMIF(#REF!,XXXXFinRep!B54,#REF!) -> #REF! | G54: =SUMIF(#REF!,XXXXFinRep!B54,#REF!)+SUMIF(#REF!,XXXXFinRep!B54,#REF!) -> #REF! | H54: =SUM(E54,F54,G54) -> #REF! | I54: =SUM(D54-H54) -> #REF!
B55: B.1 | C55: Sub-Total: Objective 1 | D55: =SUM(D35:D54) -> #REF! | E55: =SUM(E35:E54) -> #REF! | F55: =SUM(F35:F54) -> #REF! | G55: =SUM(G35:G54) -> #REF! | H55: =SUM(H35:H54) -> #REF! | I55: =SUM(I35:I54) -> #REF!
B57: 2 | C57: =VLOOKUP(B57,#REF!,2,FALSE) -> #REF!
A58: 31 | B58: =VLOOKUP(A58,#REF!,2,FALSE) -> #REF! | C58: =VLOOKUP(B58,#REF!,2,FALSE) -> #REF! | D58: =SUMIF(#REF!,XXXXFinRep!B58,#REF!) -> #REF! | E58: =SUMIF(#REF!,XXXXFinRep!B58,#REF!)+SUMIF(#REF!,XXXXFinRep!B58,#REF!) -> #REF! | F58: =SUMIF(#REF!,XXXXFinRep!B58,#REF!)+SUMIF(#REF!,XXXXFinRep!B58,#REF!) -> #REF! | G58: =SUMIF(#REF!,XXXXFinRep!B58,#REF!)+SUMIF(#REF!,XXXXFinRep!B58,#REF!) -> #REF! | H58: =SUM(E58,F58,G58) -> #REF! | I58: =SUM(D58-H58) -> #REF!
A59: 32 | B59: =VLOOKUP(A59,#REF!,2,FALSE) -> #REF! | C59: =VLOOKUP(B59,#REF!,2,FALSE) -> #REF! | D59: =SUMIF(#REF!,XXXXFinRep!B59,#REF!) -> #REF! | E59: =SUMIF(#REF!,XXXXFinRep!B59,#REF!)+SUMIF(#REF!,XXXXFinRep!B59,#REF!) -> #REF! | F59: =SUMIF(#REF!,XXXXFinRep!B59,#REF!)+SUMIF(#REF!,XXXXFinRep!B59,#REF!) -> #REF! | G59: =SUMIF(#REF!,XXXXFinRep!B59,#REF!)+SUMIF(#REF!,XXXXFinRep!B59,#REF!) -> #REF! | H59: =SUM(E59,F59,G59) -> #REF! | I59: =SUM(D59-H59) -> #REF!
A60: 33 | B60: =VLOOKUP(A60,#REF!,2,FALSE) -> #REF! | C60: =VLOOKUP(B60,#REF!,2,FALSE) -> #REF! | D60: =SUMIF(#REF!,XXXXFinRep!B60,#REF!) -> #REF! | E60: =SUMIF(#REF!,XXXXFinRep!B60,#REF!)+SUMIF(#REF!,XXXXFinRep!B60,#REF!) -> #REF! | F60: =SUMIF(#REF!,XXXXFinRep!B60,#REF!)+SUMIF(#REF!,XXXXFinRep!B60,#REF!) -> #REF! | G60: =SUMIF(#REF!,XXXXFinRep!B60,#REF!)+SUMIF(#REF!,XXXXFinRep!B60,#REF!) -> #REF! | H60: =SUM(E60,F60,G60) -> #REF! | I60: =SUM(D60-H60) -> #REF!
A61: 34 | B61: =VLOOKUP(A61,#REF!,2,FALSE) -> #REF! | C61: =VLOOKUP(B61,#REF!,2,FALSE) -> #REF! | D61: =SUMIF(#REF!,XXXXFinRep!B61,#REF!) -> #REF! | E61: =SUMIF(#REF!,XXXXFinRep!B61,#REF!)+SUMIF(#REF!,XXXXFinRep!B61,#REF!) -> #REF! | F61: =SUMIF(#REF!,XXXXFinRep!B61,#REF!)+SUMIF(#REF!,XXXXFinRep!B61,#REF!) -> #REF! | G61: =SUMIF(#REF!,XXXXFinRep!B61,#REF!)+SUMIF(#REF!,XXXXFinRep!B61,#REF!) -> #REF! | H61: =SUM(E61,F61,G61) -> #REF! | I61: =SUM(D61-H61) -> #REF!
A62: 35 | B62: =VLOOKUP(A62,#REF!,2,FALSE) -> #REF! | C62: =VLOOKUP(B62,#REF!,2,FALSE) -> #REF! | D62: =SUMIF(#REF!,XXXXFinRep!B62,#REF!) -> #REF! | E62: =SUMIF(#REF!,XXXXFinRep!B62,#REF!)+SUMIF(#REF!,XXXXFinRep!B62,#REF!) -> #REF! | F62: =SUMIF(#REF!,XXXXFinRep!B62,#REF!)+SUMIF(#REF!,XXXXFinRep!B62,#REF!) -> #REF! | G62: =SUMIF(#REF!,XXXXFinRep!B62,#REF!)+SUMIF(#REF!,XXXXFinRep!B62,#REF!) -> #REF! | H62: =SUM(E62,F62,G62) -> #REF! | I62: =SUM(D62-H62) -> #REF!
A63: 36 | B63: =VLOOKUP(A63,#REF!,2,FALSE) -> #REF! | C63: =VLOOKUP(B63,#REF!,2,FALSE) -> #REF! | D63: =SUMIF(#REF!,XXXXFinRep!B63,#REF!) -> #REF! | E63: =SUMIF(#REF!,XXXXFinRep!B63,#REF!)+SUMIF(#REF!,XXXXFinRep!B63,#REF!) -> #REF! | F63: =SUMIF(#REF!,XXXXFinRep!B63,#REF!)+SUMIF(#REF!,XXXXFinRep!B63,#REF!) -> #REF! | G63: =SUMIF(#REF!,XXXXFinRep!B63,#REF!)+SUMIF(#REF!,XXXXFinRep!B63,#REF!) -> #REF! | H63: =SUM(E63,F63,G63) -> #REF! | I63: =SUM(D63-H63) -> #REF!
A64: 37 | B64: =VLOOKUP(A64,#REF!,2,FALSE) -> #REF! | C64: =VLOOKUP(B64,#REF!,2,FALSE) -> #REF! | D64: =SUMIF(#REF!,XXXXFinRep!B64,#REF!) -> #REF! | E64: =SUMIF(#REF!,XXXXFinRep!B64,#REF!)+SUMIF(#REF!,XXXXFinRep!B64,#REF!) -> #REF! | F64: =SUMIF(#REF!,XXXXFinRep!B64,#REF!)+SUMIF(#REF!,XXXXFinRep!B64,#REF!) -> #REF! | G64: =SUMIF(#REF!,XXXXFinRep!B64,#REF!)+SUMIF(#REF!,XXXXFinRep!B64,#REF!) -> #REF! | H64: =SUM(E64,F64,G64) -> #REF! | I64: =SUM(D64-H64) -> #REF!
A65: 38 | B65: =VLOOKUP(A65,#REF!,2,FALSE) -> #REF! | C65: =VLOOKUP(B65,#REF!,2,FALSE) -> #REF! | D65: =SUMIF(#REF!,XXXXFinRep!B65,#REF!) -> #REF! | E65: =SUMIF(#REF!,XXXXFinRep!B65,#REF!)+SUMIF(#REF!,XXXXFinRep!B65,#REF!) -> #REF! | F65: =SUMIF(#REF!,XXXXFinRep!B65,#REF!)+SUMIF(#REF!,XXXXFinRep!B65,#REF!) -> #REF! | G65: =SUMIF(#REF!,XXXXFinRep!B65,#REF!)+SUMIF(#REF!,XXXXFinRep!B65,#REF!) -> #REF! | H65: =SUM(E65,F65,G65) -> #REF! | I65: =SUM(D65-H65) -> #REF!
A66: 39 | B66: =VLOOKUP(A66,#REF!,2,FALSE) -> #REF! | C66: =VLOOKUP(B66,#REF!,2,FALSE) -> #REF! | D66: =SUMIF(#REF!,XXXXFinRep!B66,#REF!) -> #REF! | E66: =SUMIF(#REF!,XXXXFinRep!B66,#REF!)+SUMIF(#REF!,XXXXFinRep!B66,#REF!) -> #REF! | F66: =SUMIF(#REF!,XXXXFinRep!B66,#REF!)+SUMIF(#REF!,XXXXFinRep!B66,#REF!) -> #REF! | G66: =SUMIF(#REF!,XXXXFinRep!B66,#REF!)+SUMIF(#REF!,XXXXFinRep!B66,#REF!) -> #REF! | H66: =SUM(E66,F66,G66) -> #REF! | I66: =SUM(D66-H66) -> #REF!
A67: 40 | B67: =VLOOKUP(A67,#REF!,2,FALSE) -> #REF! | C67: =VLOOKUP(B67,#REF!,2,FALSE) -> #REF! | D67: =SUMIF(#REF!,XXXXFinRep!B67,#REF!) -> #REF! | E67: =SUMIF(#REF!,XXXXFinRep!B67,#REF!)+SUMIF(#REF!,XXXXFinRep!B67,#REF!) -> #REF! | F67: =SUMIF(#REF!,XXXXFinRep!B67,#REF!)+SUMIF(#REF!,XXXXFinRep!B67,#REF!) -> #REF! | G67: =SUMIF(#REF!,XXXXFinRep!B67,#REF!)+SUMIF(#REF!,XXXXFinRep!B67,#REF!) -> #REF! | H67: =SUM(E67,F67,G67) -> #REF! | I67: =SUM(D67-H67) -> #REF!
A68: 41 | B68: =VLOOKUP(A68,#REF!,2,FALSE) -> #REF! | C68: =VLOOKUP(B68,#REF!,2,FALSE) -> #REF! | D68: =SUMIF(#REF!,XXXXFinRep!B68,#REF!) -> #REF! | E68: =SUMIF(#REF!,XXXXFinRep!B68,#REF!)+SUMIF(#REF!,XXXXFinRep!B68,#REF!) -> #REF! | F68: =SUMIF(#REF!,XXXXFinRep!B68,#REF!)+SUMIF(#REF!,XXXXFinRep!B68,#REF!) -> #REF! | G68: =SUMIF(#REF!,XXXXFinRep!B68,#REF!)+SUMIF(#REF!,XXXXFinRep!B68,#REF!) -> #REF! | H68: =SUM(E68,F68,G68) -> #REF! | I68: =SUM(D68-H68) -> #REF!
A69: 42 | B69: =VLOOKUP(A69,#REF!,2,FALSE) -> #REF! | C69: =VLOOKUP(B69,#REF!,2,FALSE) -> #REF! | D69: =SUMIF(#REF!,XXXXFinRep!B69,#REF!) -> #REF! | E69: =SUMIF(#REF!,XXXXFinRep!B69,#REF!)+SUMIF(#REF!,XXXXFinRep!B69,#REF!) -> #REF! | F69: =SUMIF(#REF!,XXXXFinRep!B69,#REF!)+SUMIF(#REF!,XXXXFinRep!B69,#REF!) -> #REF! | G69: =SUMIF(#REF!,XXXXFinRep!B69,#REF!)+SUMIF(#REF!,XXXXFinRep!B69,#REF!) -> #REF! | H69: =SUM(E69,F69,G69) -> #REF! | I69: =SUM(D69-H69) -> #REF!
... A77: 50 | B77: =VLOOKUP(A77,#REF!,2,FALSE) -> #REF! | C77: =VLOOKUP(B77,#REF!,2,FALSE) -> #REF! | D77: =SUMIF(#REF!,XXXXFinRep!B77,#REF!) -> #REF! | E77: =SUMIF(#REF!,XXXXFinRep!B77,#REF!)+SUMIF(#REF!,XXXXFinRep!B77,#REF!) -> #REF! | F77: =SUMIF(#REF!,XXXXFinRep!B77,#REF!)+SUMIF(#REF!,XXXXFinRep!B77,#REF!) -> #REF! | G77: =SUMIF(#REF!,XXXXFinRep!B77,#REF!)+SUMIF(#REF!,XXXXFinRep!B77,#REF!) -> #REF! | H77: =SUM(E77,F77,G77) -> #REF! | I77: =SUM(D77-H77) -> #REF!
B78: B.2 | C78: Sub-Total: Objective 2 | D78: =SUM(D58:D77) -> #REF! | E78: =SUM(E58:E77) -> #REF! | F78: =SUM(F58:F77) -> #REF! | G78: =SUM(G58:G77) -> #REF! | H78: =SUM(H58:H77) -> #REF! | I78: =SUM(I58:I77) -> #REF!
B80: 3 | C80: =VLOOKUP(B80,#REF!,2,FALSE) -> #REF!
A81: 51 | B81: =VLOOKUP(A81,#REF!,2,FALSE) -> #REF! | C81: =VLOOKUP(B81,#REF!,2,FALSE) -> #REF! | D81: =SUMIF(#REF!,XXXXFinRep!B81,#REF!) -> #REF! | E81: =SUMIF(#REF!,XXXXFinRep!B81,#REF!)+SUMIF(#REF!,XXXXFinRep!B81,#REF!) -> #REF! | F81: =SUMIF(#REF!,XXXXFinRep!B81,#REF!)+SUMIF(#REF!,XXXXFinRep!B81,#REF!) -> #REF! | G81: =SUMIF(#REF!,XXXXFinRep!B81,#REF!)+SUMIF(#REF!,XXXXFinRep!B81,#REF!) -> #REF! | H81: =SUM(E81,F81,G81) -> #REF! | I81: =SUM(D81-H81) -> #REF!
A82: 52 | B82: =VLOOKUP(A82,#REF!,2,FALSE) -> #REF! | C82: =VLOOKUP(B82,#REF!,2,FALSE) -> #REF! | D82: =SUMIF(#REF!,XXXXFinRep!B82,#REF!) -> #REF! | E82: =SUMIF(#REF!,XXXXFinRep!B82,#REF!)+SUMIF(#REF!,XXXXFinRep!B82,#REF!) -> #REF! | F82: =SUMIF(#REF!,XXXXFinRep!B82,#REF!)+SUMIF(#REF!,XXXXFinRep!B82,#REF!) -> #REF! | G82: =SUMIF(#REF!,XXXXFinRep!B82,#REF!)+SUMIF(#REF!,XXXXFinRep!B82,#REF!) -> #REF! | H82: =SUM(E82,F82,G82) -> #REF! | I82: =SUM(D82-H82) -> #REF!
A83: 53 | B83: =VLOOKUP(A83,#REF!,2,FALSE) -> #REF! | C83: =VLOOKUP(B83,#REF!,2,FALSE) -> #REF! | D83: =SUMIF(#REF!,XXXXFinRep!B83,#REF!) -> #REF! | E83: =SUMIF(#REF!,XXXXFinRep!B83,#REF!)+SUMIF(#REF!,XXXXFinRep!B83,#REF!) -> #REF! | F83: =SUMIF(#REF!,XXXXFinRep!B83,#REF!)+SUMIF(#REF!,XXXXFinRep!B83,#REF!) -> #REF! | G83: =SUMIF(#REF!,XXXXFinRep!B83,#REF!)+SUMIF(#REF!,XXXXFinRep!B83,#REF!) -> #REF! | H83: =SUM(E83,F83,G83) -> #REF! | I83: =SUM(D83-H83) -> #REF!
A84: 54 | B84: =VLOOKUP(A84,#REF!,2,FALSE) -> #REF! | C84: =VLOOKUP(B84,#REF!,2,FALSE) -> #REF! | D84: =SUMIF(#REF!,XXXXFinRep!B84,#REF!) -> #REF! | E84: =SUMIF(#REF!,XXXXFinRep!B84,#REF!)+SUMIF(#REF!,XXXXFinRep!B84,#REF!) -> #REF! | F84: =SUMIF(#REF!,XXXXFinRep!B84,#REF!)+SUMIF(#REF!,XXXXFinRep!B84,#REF!) -> #REF! | G84: =SUMIF(#REF!,XXXXFinRep!B84,#REF!)+SUMIF(#REF!,XXXXFinRep!B84,#REF!) -> #REF! | H84: =SUM(E84,F84,G84) -> #REF! | I84: =SUM(D84-H84) -> #REF!
A85: 55 | B85: =VLOOKUP(A85,#REF!,2,FALSE) -> #REF! | C85: =VLOOKUP(B85,#REF!,2,FALSE) -> #REF! | D85: =SUMIF(#REF!,XXXXFinRep!B85,#REF!) -> #REF! | E85: =SUMIF(#REF!,XXXXFinRep!B85,#REF!)+SUMIF(#REF!,XXXXFinRep!B85,#REF!) -> #REF! | F85: =SUMIF(#REF!,XXXXFinRep!B85,#REF!)+SUMIF(#REF!,XXXXFinRep!B85,#REF!) -> #REF! | G85: =SUMIF(#REF!,XXXXFinRep!B85,#REF!)+SUMIF(#REF!,XXXXFinRep!B85,#REF!) -> #REF! | H85: =SUM(E85,F85,G85) -> #REF! | I85: =SUM(D85-H85) -> #REF!
A86: 56 | B86: =VLOOKUP(A86,#REF!,2,FALSE) -> #REF! | C86: =VLOOKUP(B86,#REF!,2,FALSE) -> #REF! | D86: =SUMIF(#REF!,XXXXFinRep!B86,#REF!) -> #REF! | E86: =SUMIF(#REF!,XXXXFinRep!B86,#REF!)+SUMIF(#REF!,XXXXFinRep!B86,#REF!) -> #REF! | F86: =SUMIF(#REF!,XXXXFinRep!B86,#REF!)+SUMIF(#REF!,XXXXFinRep!B86,#REF!) -> #REF! | G86: =SUMIF(#REF!,XXXXFinRep!B86,#REF!)+SUMIF(#REF!,XXXXFinRep!B86,#REF!) -> #REF! | H86: =SUM(E86,F86,G86) -> #REF! | I86: =SUM(D86-H86) -> #REF!
A87: 57 | B87: =VLOOKUP(A87,#REF!,2,FALSE) -> #REF! | C87: =VLOOKUP(B87,#REF!,2,FALSE) -> #REF! | D87: =SUMIF(#REF!,XXXXFinRep!B87,#REF!) -> #REF! | E87: =SUMIF(#REF!,XXXXFinRep!B87,#REF!)+SUMIF(#REF!,XXXXFinRep!B87,#REF!) -> #REF! | F87: =SUMIF(#REF!,XXXXFinRep!B87,#REF!)+SUMIF(#REF!,XXXXFinRep!B87,#REF!) -> #REF! | G87: =SUMIF(#REF!,XXXXFinRep!B87,#REF!)+SUMIF(#REF!,XXXXFinRep!B87,#REF!) -> #REF! | H87: =SUM(E87,F87,G87) -> #REF! | I87: =SUM(D87-H87) -> #REF!
A88: 58 | B88: =VLOOKUP(A88,#REF!,2,FALSE) -> #REF! | C88: =VLOOKUP(B88,#REF!,2,FALSE) -> #REF! | D88: =SUMIF(#REF!,XXXXFinRep!B88,#REF!) -> #REF! | E88: =SUMIF(#REF!,XXXXFinRep!B88,#REF!)+SUMIF(#REF!,XXXXFinRep!B88,#REF!) -> #REF! | F88: =SUMIF(#REF!,XXXXFinRep!B88,#REF!)+SUMIF(#REF!,XXXXFinRep!B88,#REF!) -> #REF! | G88: =SUMIF(#REF!,XXXXFinRep!B88,#REF!)+SUMIF(#REF!,XXXXFinRep!B88,#REF!) -> #REF! | H88: =SUM(E88,F88,G88) -> #REF! | I88: =SUM(D88-H88) -> #REF!
A89: 59 | B89: =VLOOKUP(A89,#REF!,2,FALSE) -> #REF! | C89: =VLOOKUP(B89,#REF!,2,FALSE) -> #REF! | D89: =SUMIF(#REF!,XXXXFinRep!B89,#REF!) -> #REF! | E89: =SUMIF(#REF!,XXXXFinRep!B89,#REF!)+SUMIF(#REF!,XXXXFinRep!B89,#REF!) -> #REF! | F89: =SUMIF(#REF!,XXXXFinRep!B89,#REF!)+SUMIF(#REF!,XXXXFinRep!B89,#REF!) -> #REF! | G89: =SUMIF(#REF!,XXXXFinRep!B89,#REF!)+SUMIF(#REF!,XXXXFinRep!B89,#REF!) -> #REF! | H89: =SUM(E89,F89,G89) -> #REF! | I89: =SUM(D89-H89) -> #REF!
A90: 60 | B90: =VLOOKUP(A90,#REF!,2,FALSE) -> #REF! | C90: =VLOOKUP(B90,#REF!,2,FALSE) -> #REF! | D90: =SUMIF(#REF!,XXXXFinRep!B90,#REF!) -> #REF! | E90: =SUMIF(#REF!,XXXXFinRep!B90,#REF!)+SUMIF(#REF!,XXXXFinRep!B90,#REF!) -> #REF! | F90: =SUMIF(#REF!,XXXXFinRep!B90,#REF!)+SUMIF(#REF!,XXXXFinRep!B90,#REF!) -> #REF! | G90: =SUMIF(#REF!,XXXXFinRep!B90,#REF!)+SUMIF(#REF!,XXXXFinRep!B90,#REF!) -> #REF! | H90: =SUM(E90,F90,G90) -> #REF! | I90: =SUM(D90-H90) -> #REF!
A91: 61 | B91: =VLOOKUP(A91,#REF!,2,FALSE) -> #REF! | C91: =VLOOKUP(B91,#REF!,2,FALSE) -> #REF! | D91: =SUMIF(#REF!,XXXXFinRep!B91,#REF!) -> #REF! | E91: =SUMIF(#REF!,XXXXFinRep!B91,#REF!)+SUMIF(#REF!,XXXXFinRep!B91,#REF!) -> #REF! | F91: =SUMIF(#REF!,XXXXFinRep!B91,#REF!)+SUMIF(#REF!,XXXXFinRep!B91,#REF!) -> #REF! | G91: =SUMIF(#REF!,XXXXFinRep!B91,#REF!)+SUMIF(#REF!,XXXXFinRep!B91,#REF!) -> #REF! | H91: =SUM(E91,F91,G91) -> #REF! | I91: =SUM(D91-H91) -> #REF!
A92: 62 | B92: =VLOOKUP(A92,#REF!,2,FALSE) -> #REF! | C92: =VLOOKUP(B92,#REF!,2,FALSE) -> #REF! | D92: =SUMIF(#REF!,XXXXFinRep!B92,#REF!) -> #REF! | E92: =SUMIF(#REF!,XXXXFinRep!B92,#REF!)+SUMIF(#REF!,XXXXFinRep!B92,#REF!) -> #REF! | F92: =SUMIF(#REF!,XXXXFinRep!B92,#REF!)+SUMIF(#REF!,XXXXFinRep!B92,#REF!) -> #REF! | G92: =SUMIF(#REF!,XXXXFinRep!B92,#REF!)+SUMIF(#REF!,XXXXFinRep!B92,#REF!) -> #REF! | H92: =SUM(E92,F92,G92) -> #REF! | I92: =SUM(D92-H92) -> #REF!
... A100: 70 | B100: =VLOOKUP(A100,#REF!,2,FALSE) -> #REF! | C100: =VLOOKUP(B100,#REF!,2,FALSE) -> #REF! | D100: =SUMIF(#REF!,XXXXFinRep!B100,#REF!) -> #REF! | E100: =SUMIF(#REF!,XXXXFinRep!B100,#REF!)+SUMIF(#REF!,XXXXFinRep!B100,#REF!) -> #REF! | F100: =SUMIF(#REF!,XXXXFinRep!B100,#REF!)+SUMIF(#REF!,XXXXFinRep!B100,#REF!) -> #REF! | G100: =SUMIF(#REF!,XXXXFinRep!B100,#REF!)+SUMIF(#REF!,XXXXFinRep!B100,#REF!) -> #REF! | H100: =SUM(E100,F100,G100) -> #REF! | I100: =SUM(D100-H100) -> #REF!
B101: B.3 | C101: Sub-Total: Objective 3 | D101: =SUM(D81:D100) -> #REF! | E101: =SUM(E81:E100) -> #REF! | F101: =SUM(F81:F100) -> #REF! | G101: =SUM(G81:G100) -> #REF! | H101: =SUM(H81:H100) -> #REF! | I101: =SUM(I81:I100) -> #REF!
B103: 4 | C103: =VLOOKUP(B103,#REF!,2,FALSE) -> #REF!
A104: 71 | B104: =VLOOKUP(A104,#REF!,2,FALSE) -> #REF! | C104: =VLOOKUP(B104,#REF!,2,FALSE) -> #REF! | D104: =SUMIF(#REF!,XXXXFinRep!B104,#REF!) -> #REF! | E104: =SUMIF(#REF!,XXXXFinRep!B104,#REF!)+SUMIF(#REF!,XXXXFinRep!B104,#REF!) -> #REF! | F104: =SUMIF(#REF!,XXXXFinRep!B104,#REF!)+SUMIF(#REF!,XXXXFinRep!B104,#REF!) -> #REF! | G104: =SUMIF(#REF!,XXXXFinRep!B104,#REF!)+SUMIF(#REF!,XXXXFinRep!B104,#REF!) -> #REF! | H104: =SUM(E104,F104,G104) -> #REF! | I104: =SUM(D104-H104) -> #REF!
A105: 72 | B105: =VLOOKUP(A105,#REF!,2,FALSE) -> #REF! | C105: =VLOOKUP(B105,#REF!,2,FALSE) -> #REF! | D105: =SUMIF(#REF!,XXXXFinRep!B105,#REF!) -> #REF! | E105: =SUMIF(#REF!,XXXXFinRep!B105,#REF!)+SUMIF(#REF!,XXXXFinRep!B105,#REF!) -> #REF! | F105: =SUMIF(#REF!,XXXXFinRep!B105,#REF!)+SUMIF(#REF!,XXXXFinRep!B105,#REF!) -> #REF! | G105: =SUMIF(#REF!,XXXXFinRep!B105,#REF!)+SUMIF(#REF!,XXXXFinRep!B105,#REF!) -> #REF! | H105: =SUM(E105,F105,G105) -> #REF! | I105: =SUM(D105-H105) -> #REF!
A106: 73 | B106: =VLOOKUP(A106,#REF!,2,FALSE) -> #REF! | C106: =VLOOKUP(B106,#REF!,2,FALSE) -> #REF! | D106: =SUMIF(#REF!,XXXXFinRep!B106,#REF!) -> #REF! | E106: =SUMIF(#REF!,XXXXFinRep!B106,#REF!)+SUMIF(#REF!,XXXXFinRep!B106,#REF!) -> #REF! | F106: =SUMIF(#REF!,XXXXFinRep!B106,#REF!)+SUMIF(#REF!,XXXXFinRep!B106,#REF!) -> #REF! | G106: =SUMIF(#REF!,XXXXFinRep!B106,#REF!)+SUMIF(#REF!,XXXXFinRep!B106,#REF!) -> #REF! | H106: =SUM(E106,F106,G106) -> #REF! | I106: =SUM(D106-H106) -> #REF!
A107: 74 | B107: =VLOOKUP(A107,#REF!,2,FALSE) -> #REF! | C107: =VLOOKUP(B107,#REF!,2,FALSE) -> #REF! | D107: =SUMIF(#REF!,XXXXFinRep!B107,#REF!) -> #REF! | E107: =SUMIF(#REF!,XXXXFinRep!B107,#REF!)+SUMIF(#REF!,XXXXFinRep!B107,#REF!) -> #REF! | F107: =SUMIF(#REF!,XXXXFinRep!B107,#REF!)+SUMIF(#REF!,XXXXFinRep!B107,#REF!) -> #REF! | G107: =SUMIF(#REF!,XXXXFinRep!B107,#REF!)+SUMIF(#REF!,XXXXFinRep!B107,#REF!) -> #REF! | H107: =SUM(E107,F107,G107) -> #REF! | I107: =SUM(D107-H107) -> #REF!
A108: 75 | B108: =VLOOKUP(A108,#REF!,2,FALSE) -> #REF! | C108: =VLOOKUP(B108,#REF!,2,FALSE) -> #REF! | D108: =SUMIF(#REF!,XXXXFinRep!B108,#REF!) -> #REF! | E108: =SUMIF(#REF!,XXXXFinRep!B108,#REF!)+SUMIF(#REF!,XXXXFinRep!B108,#REF!) -> #REF! | F108: =SUMIF(#REF!,XXXXFinRep!B108,#REF!)+SUMIF(#REF!,XXXXFinRep!B108,#REF!) -> #REF! | G108: =SUMIF(#REF!,XXXXFinRep!B108,#REF!)+SUMIF(#REF!,XXXXFinRep!B108,#REF!) -> #REF! | H108: =SUM(E108,F108,G108) -> #REF! | I108: =SUM(D108-H108) -> #REF!
A109: 76 | B109: =VLOOKUP(A109,#REF!,2,FALSE) -> #REF! | C109: =VLOOKUP(B109,#REF!,2,FALSE) -> #REF! | D109: =SUMIF(#REF!,XXXXFinRep!B109,#REF!) -> #REF! | E109: =SUMIF(#REF!,XXXXFinRep!B109,#REF!)+SUMIF(#REF!,XXXXFinRep!B109,#REF!) -> #REF! | F109: =SUMIF(#REF!,XXXXFinRep!B109,#REF!)+SUMIF(#REF!,XXXXFinRep!B109,#REF!) -> #REF! | G109: =SUMIF(#REF!,XXXXFinRep!B109,#REF!)+SUMIF(#REF!,XXXXFinRep!B109,#REF!) -> #REF! | H109: =SUM(E109,F109,G109) -> #REF! | I109: =SUM(D109-H109) -> #REF!
A110: 77 | B110: =VLOOKUP(A110,#REF!,2,FALSE) -> #REF! | C110: =VLOOKUP(B110,#REF!,2,FALSE) -> #REF! | D110: =SUMIF(#REF!,XXXXFinRep!B110,#REF!) -> #REF! | E110: =SUMIF(#REF!,XXXXFinRep!B110,#REF!)+SUMIF(#REF!,XXXXFinRep!B110,#REF!) -> #REF! | F110: =SUMIF(#REF!,XXXXFinRep!B110,#REF!)+SUMIF(#REF!,XXXXFinRep!B110,#REF!) -> #REF! | G110: =SUMIF(#REF!,XXXXFinRep!B110,#REF!)+SUMIF(#REF!,XXXXFinRep!B110,#REF!) -> #REF! | H110: =SUM(E110,F110,G110) -> #REF! | I110: =SUM(D110-H110) -> #REF!
A111: 78 | B111: =VLOOKUP(A111,#REF!,2,FALSE) -> #REF! | C111: =VLOOKUP(B111,#REF!,2,FALSE) -> #REF! | D111: =SUMIF(#REF!,XXXXFinRep!B111,#REF!) -> #REF! | E111: =SUMIF(#REF!,XXXXFinRep!B111,#REF!)+SUMIF(#REF!,XXXXFinRep!B111,#REF!) -> #REF! | F111: =SUMIF(#REF!,XXXXFinRep!B111,#REF!)+SUMIF(#REF!,XXXXFinRep!B111,#REF!) -> #REF! | G111: =SUMIF(#REF!,XXXXFinRep!B111,#REF!)+SUMIF(#REF!,XXXXFinRep!B111,#REF!) -> #REF! | H111: =SUM(E111,F111,G111) -> #REF! | I111: =SUM(D111-H111) -> #REF!
A112: 79 | B112: =VLOOKUP(A112,#REF!,2,FALSE) -> #REF! | C112: =VLOOKUP(B112,#REF!,2,FALSE) -> #REF! | D112: =SUMIF(#REF!,XXXXFinRep!B112,#REF!) -> #REF! | E112: =SUMIF(#REF!,XXXXFinRep!B112,#REF!)+SUMIF(#REF!,XXXXFinRep!B112,#REF!) -> #REF! | F112: =SUMIF(#REF!,XXXXFinRep!B112,#REF!)+SUMIF(#REF!,XXXXFinRep!B112,#REF!) -> #REF! | G112: =SUMIF(#REF!,XXXXFinRep!B112,#REF!)+SUMIF(#REF!,XXXXFinRep!B112,#REF!) -> #REF! | H112: =SUM(E112,F112,G112) -> #REF! | I112: =SUM(D112-H112) -> #REF!
A113: 80 | B113: =VLOOKUP(A113,#REF!,2,FALSE) -> #REF! | C113: =VLOOKUP(B113,#REF!,2,FALSE) -> #REF! | D113: =SUMIF(#REF!,XXXXFinRep!B113,#REF!) -> #REF! | E113: =SUMIF(#REF!,XXXXFinRep!B113,#REF!)+SUMIF(#REF!,XXXXFinRep!B113,#REF!) -> #REF! | F113: =SUMIF(#REF!,XXXXFinRep!B113,#REF!)+SUMIF(#REF!,XXXXFinRep!B113,#REF!) -> #REF! | G113: =SUMIF(#REF!,XXXXFinRep!B113,#REF!)+SUMIF(#REF!,XXXXFinRep!B113,#REF!) -> #REF! | H113: =SUM(E113,F113,G113) -> #REF! | I113: =SUM(D113-H113) -> #REF!
A114: 81 | B114: =VLOOKUP(A114,#REF!,2,FALSE) -> #REF! | C114: =VLOOKUP(B114,#REF!,2,FALSE) -> #REF! | D114: =SUMIF(#REF!,XXXXFinRep!B114,#REF!) -> #REF! | E114: =SUMIF(#REF!,XXXXFinRep!B114,#REF!)+SUMIF(#REF!,XXXXFinRep!B114,#REF!) -> #REF! | F114: =SUMIF(#REF!,XXXXFinRep!B114,#REF!)+SUMIF(#REF!,XXXXFinRep!B114,#REF!) -> #REF! | G114: =SUMIF(#REF!,XXXXFinRep!B114,#REF!)+SUMIF(#REF!,XXXXFinRep!B114,#REF!) -> #REF! | H114: =SUM(E114,F114,G114) -> #REF! | I114: =SUM(D114-H114) -> #REF!
A115: 82 | B115: =VLOOKUP(A115,#REF!,2,FALSE) -> #REF! | C115: =VLOOKUP(B115,#REF!,2,FALSE) -> #REF! | D115: =SUMIF(#REF!,XXXXFinRep!B115,#REF!) -> #REF! | E115: =SUMIF(#REF!,XXXXFinRep!B115,#REF!)+SUMIF(#REF!,XXXXFinRep!B115,#REF!) -> #REF! | F115: =SUMIF(#REF!,XXXXFinRep!B115,#REF!)+SUMIF(#REF!,XXXXFinRep!B115,#REF!) -> #REF! | G115: =SUMIF(#REF!,XXXXFinRep!B115,#REF!)+SUMIF(#REF!,XXXXFinRep!B115,#REF!) -> #REF! | H115: =SUM(E115,F115,G115) -> #REF! | I115: =SUM(D115-H115) -> #REF!
... A123: 90 | B123: =VLOOKUP(A123,#REF!,2,FALSE) -> #REF! | C123: =VLOOKUP(B123,#REF!,2,FALSE) -> #REF! | D123: =SUMIF(#REF!,XXXXFinRep!B123,#REF!) -> #REF! | E123: =SUMIF(#REF!,XXXXFinRep!B123,#REF!)+SUMIF(#REF!,XXXXFinRep!B123,#REF!) -> #REF! | F123: =SUMIF(#REF!,XXXXFinRep!B123,#REF!)+SUMIF(#REF!,XXXXFinRep!B123,#REF!) -> #REF! | G123: =SUMIF(#REF!,XXXXFinRep!B123,#REF!)+SUMIF(#REF!,XXXXFinRep!B123,#REF!) -> #REF! | H123: =SUM(E123,F123,G123) -> #REF! | I123: =SUM(D123-H123) -> #REF!
B124: B.4 | C124: Sub-Total: Objective 4 | D124: =SUM(D104:D123) -> #REF! | E124: =SUM(E104:E123) -> #REF! | F124: =SUM(F104:F123) -> #REF! | G124: =SUM(G104:G123) -> #REF! | H124: =SUM(H104:H123) -> #REF! | I124: =SUM(I104:I123) -> #REF!
B126: 5 | C126: =VLOOKUP(B126,#REF!,2,FALSE) -> #REF!
A127: 91 | B127: =VLOOKUP(A127,#REF!,2,FALSE) -> #REF! | C127: =VLOOKUP(B127,#REF!,2,FALSE) -> #REF! | D127: =SUMIF(#REF!,XXXXFinRep!B127,#REF!) -> #REF! | E127: =SUMIF(#REF!,XXXXFinRep!B127,#REF!)+SUMIF(#REF!,XXXXFinRep!B127,#REF!) -> #REF! | F127: =SUMIF(#REF!,XXXXFinRep!B127,#REF!)+SUMIF(#REF!,XXXXFinRep!B127,#REF!) -> #REF! | G127: =SUMIF(#REF!,XXXXFinRep!B127,#REF!)+SUMIF(#REF!,XXXXFinRep!B127,#REF!) -> #REF! | H127: =SUM(E127,F127,G127) -> #REF! | I127: =SUM(D127-H127) -> #REF!
A128: 92 | B128: =VLOOKUP(A128,#REF!,2,FALSE) -> #REF! | C128: =VLOOKUP(B128,#REF!,2,FALSE) -> #REF! | D128: =SUMIF(#REF!,XXXXFinRep!B128,#REF!) -> #REF! | E128: =SUMIF(#REF!,XXXXFinRep!B128,#REF!)+SUMIF(#REF!,XXXXFinRep!B128,#REF!) -> #REF! | F128: =SUMIF(#REF!,XXXXFinRep!B128,#REF!)+SUMIF(#REF!,XXXXFinRep!B128,#REF!) -> #REF! | G128: =SUMIF(#REF!,XXXXFinRep!B128,#REF!)+SUMIF(#REF!,XXXXFinRep!B128,#REF!) -> #REF! | H128: =SUM(E128,F128,G128) -> #REF! | I128: =SUM(D128-H128) -> #REF!
A129: 93 | B129: =VLOOKUP(A129,#REF!,2,FALSE) -> #REF! | C129: =VLOOKUP(B129,#REF!,2,FALSE) -> #REF! | D129: =SUMIF(#REF!,XXXXFinRep!B129,#REF!) -> #REF! | E129: =SUMIF(#REF!,XXXXFinRep!B129,#REF!)+SUMIF(#REF!,XXXXFinRep!B129,#REF!) -> #REF! | F129: =SUMIF(#REF!,XXXXFinRep!B129,#REF!)+SUMIF(#REF!,XXXXFinRep!B129,#REF!) -> #REF! | G129: =SUMIF(#REF!,XXXXFinRep!B129,#REF!)+SUMIF(#REF!,XXXXFinRep!B129,#REF!) -> #REF! | H129: =SUM(E129,F129,G129) -> #REF! | I129: =SUM(D129-H129) -> #REF!
A130: 94 | B130: =VLOOKUP(A130,#REF!,2,FALSE) -> #REF! | C130: =VLOOKUP(B130,#REF!,2,FALSE) -> #REF! | D130: =SUMIF(#REF!,XXXXFinRep!B130,#REF!) -> #REF! | E130: =SUMIF(#REF!,XXXXFinRep!B130,#REF!)+SUMIF(#REF!,XXXXFinRep!B130,#REF!) -> #REF! | F130: =SUMIF(#REF!,XXXXFinRep!B130,#REF!)+SUMIF(#REF!,XXXXFinRep!B130,#REF!) -> #REF! | G130: =SUMIF(#REF!,XXXXFinRep!B130,#REF!)+SUMIF(#REF!,XXXXFinRep!B130,#REF!) -> #REF! | H130: =SUM(E130,F130,G130) -> #REF! | I130: =SUM(D130-H130) -> #REF!
A131: 95 | B131: =VLOOKUP(A131,#REF!,2,FALSE) -> #REF! | C131: =VLOOKUP(B131,#REF!,2,FALSE) -> #REF! | D131: =SUMIF(#REF!,XXXXFinRep!B131,#REF!) -> #REF! | E131: =SUMIF(#REF!,XXXXFinRep!B131,#REF!)+SUMIF(#REF!,XXXXFinRep!B131,#REF!) -> #REF! | F131: =SUMIF(#REF!,XXXXFinRep!B131,#REF!)+SUMIF(#REF!,XXXXFinRep!B131,#REF!) -> #REF! | G131: =SUMIF(#REF!,XXXXFinRep!B131,#REF!)+SUMIF(#REF!,XXXXFinRep!B131,#REF!) -> #REF! | H131: =SUM(E131,F131,G131) -> #REF! | I131: =SUM(D131-H131) -> #REF!
A132: 96 | B132: =VLOOKUP(A132,#REF!,2,FALSE) -> #REF! | C132: =VLOOKUP(B132,#REF!,2,FALSE) -> #REF! | D132: =SUMIF(#REF!,XXXXFinRep!B132,#REF!) -> #REF! | E132: =SUMIF(#REF!,XXXXFinRep!B132,#REF!)+SUMIF(#REF!,XXXXFinRep!B132,#REF!) -> #REF! | F132: =SUMIF(#REF!,XXXXFinRep!B132,#REF!)+SUMIF(#REF!,XXXXFinRep!B132,#REF!) -> #REF! | G132: =SUMIF(#REF!,XXXXFinRep!B132,#REF!)+SUMIF(#REF!,XXXXFinRep!B132,#REF!) -> #REF! | H132: =SUM(E132,F132,G132) -> #REF! | I132: =SUM(D132-H132) -> #REF!
A133: 97 | B133: =VLOOKUP(A133,#REF!,2,FALSE) -> #REF! | C133: =VLOOKUP(B133,#REF!,2,FALSE) -> #REF! | D133: =SUMIF(#REF!,XXXXFinRep!B133,#REF!) -> #REF! | E133: =SUMIF(#REF!,XXXXFinRep!B133,#REF!)+SUMIF(#REF!,XXXXFinRep!B133,#REF!) -> #REF! | F133: =SUMIF(#REF!,XXXXFinRep!B133,#REF!)+SUMIF(#REF!,XXXXFinRep!B133,#REF!) -> #REF! | G133: =SUMIF(#REF!,XXXXFinRep!B133,#REF!)+SUMIF(#REF!,XXXXFinRep!B133,#REF!) -> #REF! | H133: =SUM(E133,F133,G133) -> #REF! | I133: =SUM(D133-H133) -> #REF!
A134: 98 | B134: =VLOOKUP(A134,#REF!,2,FALSE) -> #REF! | C134: =VLOOKUP(B134,#REF!,2,FALSE) -> #REF! | D134: =SUMIF(#REF!,XXXXFinRep!B134,#REF!) -> #REF! | E134: =SUMIF(#REF!,XXXXFinRep!B134,#REF!)+SUMIF(#REF!,XXXXFinRep!B134,#REF!) -> #REF! | F134: =SUMIF(#REF!,XXXXFinRep!B134,#REF!)+SUMIF(#REF!,XXXXFinRep!B134,#REF!) -> #REF! | G134: =SUMIF(#REF!,XXXXFinRep!B134,#REF!)+SUMIF(#REF!,XXXXFinRep!B134,#REF!) -> #REF! | H134: =SUM(E134,F134,G134) -> #REF! | I134: =SUM(D134-H134) -> #REF!
A135: 99 | B135: =VLOOKUP(A135,#REF!,2,FALSE) -> #REF! | C135: =VLOOKUP(B135,#REF!,2,FALSE) -> #REF! | D135: =SUMIF(#REF!,XXXXFinRep!B135,#REF!) -> #REF! | E135: =SUMIF(#REF!,XXXXFinRep!B135,#REF!)+SUMIF(#REF!,XXXXFinRep!B135,#REF!) -> #REF! | F135: =SUMIF(#REF!,XXXXFinRep!B135,#REF!)+SUMIF(#REF!,XXXXFinRep!B135,#REF!) -> #REF! | G135: =SUMIF(#REF!,XXXXFinRep!B135,#REF!)+SUMIF(#REF!,XXXXFinRep!B135,#REF!) -> #REF! | H135: =SUM(E135,F135,G135) -> #REF! | I135: =SUM(D135-H135) -> #REF!
A136: 100 | B136: =VLOOKUP(A136,#REF!,2,FALSE) -> #REF! | C136: =VLOOKUP(B136,#REF!,2,FALSE) -> #REF! | D136: =SUMIF(#REF!,XXXXFinRep!B136,#REF!) -> #REF! | E136: =SUMIF(#REF!,XXXXFinRep!B136,#REF!)+SUMIF(#REF!,XXXXFinRep!B136,#REF!) -> #REF! | F136: =SUMIF(#REF!,XXXXFinRep!B136,#REF!)+SUMIF(#REF!,XXXXFinRep!B136,#REF!) -> #REF! | G136: =SUMIF(#REF!,XXXXFinRep!B136,#REF!)+SUMIF(#REF!,XXXXFinRep!B136,#REF!) -> #REF! | H136: =SUM(E136,F136,G136) -> #REF! | I136: =SUM(D136-H136) -> #REF!
...

Sheet REQ ZG UMCOR 4 _RU
B2: Church World Service
B3: DETAIL BUDGET
B4: Project Title: CWS 2025 Ukraine Response Program – Serbia and Moldova
B5: Project Period: 1 Jan 2025 to 31 Dec 2025 | H5: Rev. 3/23
C7: Дата начала: 1 Февраль 2026 | D7: Дата окончания: 1 Август 2026
B8: CODE | C8: DESCRIPTION | H8: APPROVED INCOME
B9: UMCOR | C9: UMCOR Sources
B10: GRA | C10: Other Grants | H10: 0
B11: ANC | C11: Annual Conference - UMC | H11: 0
B12: PAC | C12: Partner Annual Conference Contribution | H12: 0
B13: MoH | C13: Ministry of Health/Government | H13: 0
B14: LC | C14: Local Churches and Individuals | H14: 0
B15: OTH | C15: Others-In-Kind Donation/Matching Funds | H15: =H132 -> 0
C16: TOTAL INCOME | H16: =H134 -> 58999
B19: CODE | C19: BUDGET DESCRIPTION | D19: UNIT MEASURE | E19: QUANTITY | F19: UNIT COST | G19: FREQUENCY/#MONTH/ DAY | H19: TOTAL | I19: BUDGET NOTES
B20: SECTION A: PROGRAM PERSONNEL
C21: Position
H22: 0
B24: SECTION B: DIRECT PROGRAM COSTS
B25: 1 | C25: Objective 1: To meet basic needs of refugees and migrants affected
C26: Sub-Total: Objective 1 | H26: 0
B27: 1 | C27: Objective 2: Cash Assistance
A28: 21 | B28: PRG11 | C28: Закупка/Выдача Ваучеров / Vouchers | D28: Lump sum | E28: 1 | F28: 5000 | G28: 1 | H28: =E28*F28*G28 -> 5000 | I28: Закупка ваучеров METRO (300 MDL/Ваучер), планируется выдать 281 ваучер в течении 6 месяцев проектной деятельности
A29: 22 | B29: PRG21 | C29: Супервайзер - Молдова | D29: Person/FTE | E29: 1.9 | F29: 610 | G29: 6 | H29: =E29*F29*G29 -> 6954 | I29: 2 позиция. Контролирует MHPSS (1.0 FTE) Будулай; Курирует ведение дел (0.9 FTE) Валя
A30: 23 | B30: PRG22 | C30: Зарплата юриста центра ZG -Молдова | D30: Person/FTE | E30: 0.125 | F30: 1000 | G30: 6 | H30: =E30*F30*G30 -> 750 | I30: 0.125 FTE, 1 позиция. Обеспечивает соблюдение всех применимых законов и нормативных актов.
A31: 24 | B31: PRG23 | C31: Расходы на коммунальные услуги ZG -Молдова | D31: Month | E31: 1 | F31: 600 | G31: 6 | H31: =E31*F31*G31 -> 3600 | I31: Свет, вода, тепло, интернет
A32: 25 | B32: PRG24 | C32: ZG аренда -Молдова | D32: Month | E32: 1 | F32: 550 | G32: 6 | H32: =E32*F32*G32 -> 3300 | I32: Ежемесячная стоимость аренды помещения в центре программы
A33: 26 | B33: PRG25 | C33: ZG Чистящие средства -Молдова | D33: Month | E33: 0.5 | F33: 50 | G33: 6 | H33: =E33*F33*G33 -> 150 | I33: Чистящие средства для ZG
A34: 27 | B34: PRG26 | C34: ZG питьевая вода -Молдова | D34: Month | E34: 0.5 | F34: 70 | G34: 6 | H34: =E34*F34*G34 -> 210 | I34: Для сотрудников и клиентов
A35: 28 | B35: PRG27 | C35: Канцелярские и кухонные принадлежности ZG -Молдова | D35: Month | E35: 0.5 | F35: 50 | G35: 6 | H35: =E35*F35*G35 -> 150 | I35: Печать обязательных государственных чеков для каждого получателя, кофейных чашек и т. д.
A36: 29 | B36: PRG29 | C36: Гибкое финансирование кейс менеджмент-Молдова | D36: Month | E36: 1 | F36: 670 | G36: 6 | H36: =E36*F36*G36 -> 4020 | I36: Покрытие потребностей, определенных в СМ - профессиональное обучение, жилье, питание, лекарства и т.д.
A37: 30 | B37: PRG30 | C37: Хозяйственные работники центра | D37: Person/FTE | E37: 2 | F37: 300 | G37: 6 | H37: =E37*F37*G37 -> 3600 | I37: 1.0 FTE, 2 позиции (Андрей). Обеспечивает материально-техническую поддержку: доставка необходимых товаров (вода, кофе, печенье), мелкие ремонты, транспортировка, обслуживание центра, поддержание порядка и устранение технических неисправностей; (Виорика) Уборка помещений центра, проведение мастер классов для детей.
A38: 31 | B38: PRG21 | C38: Медиа-координатор по информационному сопровождению и работе с молодёжью (Илья) | D38: Person/FTE | E38: 1 | F38: 550 | G38: 6 | H38: =E38*F38*G38 -> 3300 | I38: 1,0 FTE, 1 позициия (Илья). Отвечает за создание и публикацию контента в Instagram и Facebook, готовит анонсы мероприятий, помогает в подготовке опросников, взаимодействует с молодёжью и участвует в организации мероприятий.
A39: 32 | B39: PRG26 | C39: Экстренный бюджет | D39: Month | E39: 1 | F39: 50 | G39: 6 | H39: =E39*F39*G39 -> 300 | I39: Закупка оборудования при поломке, замена оборудования, комплектующих, расходники центра
C40: Sub-Total: Objective 2 | H40: =SUM(H28:H39) -> 31334
C42: Objective 3: To provide shelter assistance for vulnerable refugees and migrants in need of short-term accommodation.
C43: Sub-Total: Objective 3 | H43: 0
B45: 3 | C45: Objective 4: Psychosocial, Counseling & Medical
A46: 40 | B46: PRG40 | C46: Врач ZG | D46: Person/FTE | E46: 0.25 | F46: 1200 | G46: 6 | H46: =E46*F46*G46 -> 1800 | I46: 0,25 FTE, 1 позиция. Оказывает медицинские услуги участникам программы. Михайл
A47: 41 | B47: PRG41 | C47: Психологи | D47: Person/FTE | E47: 1.5 | F47: 540 | G47: 6 | H47: =E47*F47*G47 -> 4860 | I47: 0,75 FTE, 2 позиции. Проводит индивидуальные и групповые психологические сессии для участников программы. | N47: =(H57/8)*6 -> 6783.75
A48: 42 | B48: PRG42 | C48: Программа вовлечения молодежи | D48: Month | E48: 1 | F48: 200 | G48: 6 | H48: =E48*F48*G48 -> 1200 | I48: Материалы, аренда помещений, питание для молодежи MHPSS и мероприятия по социальной интеграции
A49: 55 | B49: PRG55 | C49: ZG Мастер-классы | D49: Event | E49: 6 | F49: 60 | G49: 1 | H49: =E49*F49*G49 -> 360 | I49: Материалы (например: яйца, краска, кисти для пасхальных яиц), оборудование
A50: 56 | B50: PRG56 | C50: Специалист по работе с молождежью / Фасилитатор спортивных программ | D50: Person/FTE | E50: 0.5 | F50: 550 | G50: 6 | H50: =E50*F50*G50 -> 1650 | I50: 0,5 FTE, одна позиция. Планирует и курирует программу интеграции молодежи через спорт. Сергей
C51: Sub-Total: Objective 4 | H51: =SUM(H46:H50) -> 9870
B53: 4 | C53: Objective 5: Legal Assistance
C54: Sub-Total: Objective 5 | H54: 0
B56: 5 | C56: Objective 7: Case Management
A57: 71 | B57: PRG71 | C57: Зарплата кейс-менеджеров | D57: Person/FTE | E57: 2.25 | F57: 670 | G57: 6 | H57: =E57*F57*G57 -> 9045 | I57: 0,75 FTE, 3 позиций. Предоставляет комплексные услуги по ведению дел. (Девушки). 1 позиция 0,80 FTE (Настя) будет ответствена за анонсы, обратную связь/ Обновление информации на "Dopomoga"
C58: Sub-Total: Objective 7 | H58: =SUM(H57:H57) -> 9045
C60: TOTAL DIRECT PROGRAM COSTS | H60: =H58+H54+H51+H43+H40+H26 -> 50249
B62: SECTION C: OTHER DIRECT PROGRAM COSTS
B63: 1 | C63: Visibility & Publication Costs
A64: 102 | B64: ADM2 | C64: Обслуживание и хостинг сайта - Moldova | D64: Lump sum | E64: 1 | F64: 1250 | G64: 1 | H64: =E64*F64*G64 -> 1250 | I64: Плата за хостинг, связанная с платой за веб-сайт и коммуникации (Google Workspace)
H66: =E66*F66*G66 -> 0
H67: =E67*F67*G67 -> 0
A68: 106 | C68: Sub-Total: Visibility & Publication | H68: =SUM(H64:H67) -> 1250
B69: 2 | C69: Monitoring & Evaluation Costs
A70: 111 | B70: ADM11 | C70: Плата за услугу по поддержке сайта и базы данных | D70: Month | E70: 1 | F70: 250 | G70: 6 | H70: =E70*F70*G70 -> 1500 | I70: Обслуживание и обновление портала/базы данных (Саша и Дима)
H71: =E71*F71*G71 -> 0
H72: =E72*F72*G72 -> 0
A73: 113 | C73: Sub-Total: Monitoring & Evaluation | H73: =SUM(H70:H72) -> 1500
C75: TOTAL OTHER DIRECT PROGRAM COSTS | H75: =SUM(H73,H68) -> 2750
C77: TOTAL PROGRAM COSTS (A, B, & C): | H77: =SUM(H75,H60,H22) -> 52999
B79: SECTION D: PROGRAM SUPPORT COSTS
C81: Support Personnel
A82: 124 | B82: ADM24 | C82: Зарплата бухгалтера ZG - Молдова | D82: Person/FTE | E82: 1 | F82: 450 | G82: 6 | H82: =E82*F82*G82 -> 2700 | I82: 1.0 FTE, 1 позиция. Ведет бухгалтерский учет для СМ и МХПСС в «Здоровом городе». (Рома)
H83: =E83*F83*G83 -> 0
H84: =E84*F84*G84 -> 0
C85: Sub-Total: Support Personnel | H85: =SUM(H82:H84) -> 2700
C87: Equipment
A88: 131 | B88: ADM31 | H88: =E88*F88*G88 -> 0
A89: 132 | B89: ADM32 | H89: =E89*F89*G89 -> 0
C90: Sub-Total: Equipment | H90: =SUM(H88:H89) -> 0
C92: Office Rental and Supplies
B93: ADM45 | H93: =E93*F93*G93 -> 0
A94: 145 | B94: ADM46 | H94: =E94*F94*G94 -> 0
A95: 146 | C95: Sub-Total: Office Rental and Supplies | H95: =SUM(H93:H94) -> 0
C97: Travel
C98: Domestic
H99: =E99*F99*G99 -> 0
A100: 154 | B100: ADM55 | H100: =E100*F100*G100 -> 0
A101: 155 | B101: ADM54 | C101: Топливо, ремонт автомобиля | D101: Ежемесячно | E101: 1 | F101: 500 | G101: 6 | H101: =E101*F101*G101 -> 3000
A102: 161 | B102: ADM61 | H102: =E102*F102*G102 -> 0
A103: 162 | B103: ADM62 | H103: =E103*F103*G103 -> 0
C104: Sub-Total: Travel | H104: =SUM(H99:H103) -> 3000
C106: Communication
A107: 173 | B107: ADM73 | H107: =E107*F107*G107 -> 0
A108: 174 | B108: ADM74 | H108: =E108*F108*G108 -> 0
A109: 174 | C109: Sub-Total: Communication | H109: =SUM(H107:H108) -> 0
C111: Other Operational Costs
A112: 183 | B112: ADM83 | C112: Банковские комиссии - Молдова | D112: Month | E112: 1 | F112: 50 | G112: 6 | H112: =E112*F112*G112 -> 300 | I112: Комиссии за международные переводы и обмен валюты.
A113: 185 | B113: ADM85 | H113: =E113*F113*G113 -> 0
A114: 186 | B114: ADM86 | H114: =E114*F114*G114 -> 0
A115: 186 | C115: Sub-Total: Other Operational Costs | H115: =SUM(H112:H114) -> 300
C117: TOTAL PROGRAM SUPPORT COSTS | H117: =SUM(H115,H109,H104,H95,H90,H85) -> 6000
C119: TOTAL GRANT BUDGET (A, B, C & D): | H119: =SUM(H117,H77) -> 58999
C121: IN-KIND DONATION/MATCHING FUNDS
A122: 201 | B122: IKD1 | H122: =E122*F122*G122 -> 0
A123: 202 | B123: IKD2 | H123: =E123*F123*G123 -> 0
A124: 203 | B124: IKD3 | H124: =E124*F124*G124 -> 0
...
